cloudflare_error_page/__init__.py
cloudflare_error_page/templates/.gitignore
cloudflare_error_page/templates/main.css
cloudflare_error_page/templates/template.html
cloudflare_error_page-0.2.0.dist-info/METADATA
cloudflare_error_page-0.2.0.dist-info/WHEEL
cloudflare_error_page-0.2.0.dist-info/licenses/LICENSE.txt
cloudflare_error_page-0.2.0.dist-info/RECORD
