Metadata-Version: 2.4
Name: cloudflare-error-page
Version: 0.2.0
Summary: A customizable Cloudflare error page generator
Project-URL: Homepage, https://github.com/donlon/cloudflare-error-page
Author: Anthony Donlon
License: MIT
License-File: LICENSE.txt
Requires-Python: >=3.10
Requires-Dist: jinja2>=3.0
